citation_graph/__init__.py
citation_graph/__main__.py
citation_graph/cache_manager.py
citation_graph/citation_graph.py
citation_graph/crossref.py
citation_graph/database.py
citation_graph/paper.py
citation_graph/restful_database.py
citation_graph/semantic_scholar.py
citation_graph/static.py
citation_graph/traverser.py
citation_graph/utils.py
citation_graph/VERSION
citation_graph/version.py
citation_graph-1.2.7.dist-info/LICENSE
citation_graph-1.2.7.dist-info/WHEEL
citation_graph-1.2.7.dist-info/METADATA
citation_graph-1.2.7.dist-info/RECORD
