Metadata-Version: 2.1
Name: citation-graph
Version: 1.2.7
Summary: Create a citation graph starting from a root paper
Home-page: https://github.com/miile7/citation-graph
Author: miile7
Requires-Python: >=3.8,<4.0
Classifier: Programming Language :: Python :: 3
Classifier: Programming Language :: Python :: 3.8
Classifier: Programming Language :: Python :: 3.9
Classifier: Programming Language :: Python :: 3.10
Classifier: Programming Language :: Python :: 3.11
Requires-Dist: crossrefapi (>=1.5.0,<2.0.0)
Requires-Dist: levenshtein (>=0.20.8,<0.21.0)
Requires-Dist: networkx (>=2.8.8,<3.0.0)
Requires-Dist: pyvis (>=0.3.1,<0.4.0)
Requires-Dist: requests (>=2.28.1,<3.0.0)
Requires-Dist: types-requests (>=2.28.11.5,<3.0.0.0)
Requires-Dist: unidecode (>=1.3.6,<2.0.0)
